{
    "imgPath": "/img/",
    "doors": [{
        "name": "Бард",
        "path": "doors3/",
        "file": "M3monster001.gif"
    }, {
        "name": "Гном",
        "path": "doors3/",
        "file": "M3monster002.gif"
    }, {
        "name": "Проклятие! Посмертное проклятие",
        "path": "doors3/",
        "file": "M3monster003.gif"
    }, {
        "name": "В глубокой депрессии. -5 к монстру",
        "path": "doors3/",
        "file": "M3monster004.gif"
    }, {
        "name": "Уровень 4. Готянка",
        "path": "doors3/",
        "file": "M3monster005.gif"
    }, {
        "name": "Уровень 15. Кудзу-Ядовитый мухолов",
        "path": "doors3/",
        "file": "M3monster006.gif"
    }, {
        "name": "Бард",
        "path": "doors3/",
        "file": "M3monster007.gif"
    }, {
        "name": "Гном",
        "path": "doors3/",
        "file": "M3monster008.gif"
    }, {
        "name": "Проклятие! Взрывающиеся наколенники",
        "path": "doors3/",
        "file": "M3monster009.gif"
    }, {
        "name": "Уровень 18. Тетушка-паладин",
        "path": "doors3/",
        "file": "M3monster010.gif"
    }, {
        "name": "Уровень 4. Жвачный голем",
        "path": "doors3/",
        "file": "M3monster011.gif"
    }, {
        "name": "Уровень 3. Задира с рапирой",
        "path": "doors3/",
        "file": "M3monster012.gif"
    }, {
        "name": "Полукровка",
        "path": "doors3/",
        "file": "M3monster013.gif"
    }, {
        "name": "Бард",
        "path": "doors3/",
        "file": "M3monster014.gif"
    }, {
        "name": "Гном",
        "path": "doors3/",
        "file": "M3monster015.gif"
    }, {
        "name": "Проклятие! Голодный рюкзак",
        "path": "doors3/",
        "file": "M3monster016.gif"
    }, {
        "name": "Уровень 5. Зосланец",
        "path": "doors3/",
        "file": "M3monster017.gif"
    }, {
        "name": "Уровень 20. Кали",
        "path": "doors3/",
        "file": "M3monster018.gif"
    }, {
        "name": "Уровень 13. Деревенщина",
        "path": "doors3/",
        "file": "M3monster019.gif"
    }, {
        "name": "Монстры заняты",
        "path": "doors3/",
        "file": "M3monster020.gif"
    }, {
        "name": "Бард",
        "path": "doors3/",
        "file": "M3monster021.gif"
    }, {
        "name": "Халфлинг",
        "path": "doors3/",
        "file": "M3monster022.gif"
    }, {
        "name": "Проклятие! Временная амнезия",
        "path": "doors3/",
        "file": "M3monster023.gif"
    }, {
        "name": "Уровень 6. Бочка мартышек",
        "path": "doors3/",
        "file": "M3monster024.gif"
    }, {
        "name": "Уровень 7. Кобольды-камикадзе",
        "path": "doors3/",
        "file": "M3monster025.gif"
    }, {
        "name": "Уровень 2. Обитель жала",
        "path": "doors3/",
        "file": "M3monster026.gif"
    }, {
        "name": "Суперманчкин",
        "path": "doors3/",
        "file": "M3monster027.gif"
    }, {
        "name": "Бард",
        "path": "doors3/",
        "file": "M3monster028.gif"
    }, {
        "name": "Орк",
        "path": "doors3/",
        "file": "M3monster029.gif"
    }, {
        "name": "Проклятие! Капкан на туриста",
        "path": "doors3/",
        "file": "M3monster030.gif"
    }, {
        "name": "Уровень 2. Трясоглав",
        "path": "doors3/",
        "file": "M3monster031.gif"
    }, {
        "name": "Уровень 5. Лорд Яху",
        "path": "doors3/",
        "file": "M3monster032.gif"
    }, {
        "name": "Уровень 17. Мэрилич Монро (Андед)",
        "path": "doors3/",
        "file": "M3monster033.gif"
    }, {
        "name": "Гном",
        "path": "doors3/",
        "file": "M3monster034.gif"
    }, {
        "name": "Проклятие! Дварфский эль",
        "path": "doors3/",
        "file": "M3monster035.gif"
    }, {
        "name": "В неглиже. +5 к монстру",
        "path": "doors3/",
        "file": "M3monster036.gif"
    }, {
        "name": "Уровень 1. Золотая рыбка",
        "path": "doors3/",
        "file": "M3monster037.gif"
    }, {
        "name": "Уровень 2. Совершенно обычный милый кролик",
        "path": "doors3/",
        "file": "M3monster038.gif"
    }, {
        "name": "Нечестное богатство",
        "path": "doors3/",
        "file": "M3monster039.gif"
    }, {
        "name": "Клирик",
        "path": "doors3/",
        "file": "M3monster040.gif"
    }, {
        "name": "Вор",
        "path": "doors3/",
        "file": "M3monster041.gif"
    }, {
        "name": "Проклятие! Ловушка под твоим сундуком",
        "path": "doors3/",
        "file": "M3monster042.gif"
    }, {
        "name": "Уровень 10. Дупельгангстеры",
        "path": "doors3/",
        "file": "M3monster043.gif"
    }, {
        "name": "Уровень 8. Шовинистский боров",
        "path": "doors3/",
        "file": "M3monster044.gif"
    }, {
        "name": "Уровень 1. Палка, палка - человечек",
        "path": "doors3/",
        "file": "M3monster045.gif"
    }, {
        "name": "Дварф",
        "path": "doors3/",
        "file": "M3monster046.gif"
    }, {
        "name": "Воин",
        "path": "doors3/",
        "file": "M3monster047.gif"
    }, {
        "name": "Из ада. +5 к монстру",
        "path": "doors3/",
        "file": "M3monster048.gif"
    }, {
        "name": "Уровень 9. Дриада",
        "path": "doors3/",
        "file": "M3monster049.gif"
    }, {
        "name": "Уровень 19. Медуза",
        "path": "doors3/",
        "file": "M3monster050.gif"
    }, {
        "name": "Уровень 1. Упитый пересмешник",
        "path": "doors3/",
        "file": "M3monster051.gif"
    }, {
        "name": "Типографская ошибка",
        "path": "doors3/",
        "file": "M3monster052.gif"
    }, {
        "name": "Эльф",
        "path": "doors3/",
        "file": "M3monster053.gif"
    }, {
        "name": "Волшебник",
        "path": "doors3/",
        "file": "M3monster054.gif"
    }, {
        "name": "С огромным мечом, уничижающим монстров. +10 к монстру",
        "path": "doors3/",
        "file": "M3monster055.gif"
    }, {
        "name": "Уровень 11. Грязные геты",
        "path": "doors3/",
        "file": "M3monster056.gif"
    }, {
        "name": "Уровень 14. На-падающий медведь",
        "path": "doors3/",
        "file": "M3monster057.gif"
    }, {
        "name": "Уровень 12. Тролии мертвоморья (Андед)",
        "path": "doors3/",
        "file": "M3monster058.gif"
    }, {
        "name": "Бродячая тварь",
        "path": "doors3/",
        "file": "M3monster059.gif"
    }, {
        "name": "Гном",
        "path": "doors3/",
        "file": "M3monster060.gif"
    }, {
        "name": "Проклятие! Клирическая ошибка",
        "path": "doors3/",
        "file": "M3monster061.gif"
    }, {
        "name": "Андед. +5 к монстру",
        "path": "doors3/",
        "file": "M3monster062.gif"
    }, {
        "name": "Уровень 16. Куродемон",
        "path": "doors3/",
        "file": "M3monster063.gif"
    }, {
        "name": "Уровень 3. Вьючный крыс",
        "path": "doors3/",
        "file": "M3monster064.gif"
    }, {
        "name": "Чит!",
        "path": "doors3/",
        "file": "M3monster065.gif"
    }, {
        "name": "Бродячая тварь",
        "path": "doors3/",
        "file": "M3monster066.gif"
    }],
    "treasures": [{
        "name": "Отвратные носки",
        "path": "tres3/",
        "file": "M3gold001.gif"
    }, {
        "name": "Ядированная",
        "path": "tres3/",
        "file": "M3gold002.gif"
    }, {
        "name": "Втерся в доверие. Получи уровень",
        "path": "tres3/",
        "file": "M3gold003.gif"
    }, {
        "name": "Запретительное постановление",
        "path": "tres3/",
        "file": "M3gold004.gif"
    }, {
        "name": "Большущая лира",
        "path": "tres3/",
        "file": "M3gold005.gif"
    }, {
        "name": "Убенцы",
        "path": "tres3/",
        "file": "M3gold006.gif"
    }, {
        "name": "Угрожай сменить систему. Получи уровень",
        "path": "tres3/",
        "file": "M3gold007.gif"
    }, {
        "name": "Королевская смесь",
        "path": "tres3/",
        "file": "M3gold008.gif"
    }, {
        "name": "Нахлобушки",
        "path": "tres3/",
        "file": "M3gold009.gif"
    }, {
        "name": "Благословенная",
        "path": "tres3/",
        "file": "M3gold010.gif"
    }, {
        "name": "Другое кольцо",
        "path": "tres3/",
        "file": "M3gold011.gif"
    }, {
        "name": "Дварфозаброс",
        "path": "tres3/",
        "file": "M3gold012.gif"
    }, {
        "name": "Удар без учета амортизации",
        "path": "tres3/",
        "file": "M3gold013.gif"
    }, {
        "name": "Тапочки по Фрейду",
        "path": "tres3/",
        "file": "M3gold014.gif"
    }, {
        "name": "Кольчужное бикини",
        "path": "tres3/",
        "file": "M3gold015.gif"
    }, {
        "name": "Двуручный меч",
        "path": "tres3/",
        "file": "M3gold016.gif"
    }, {
        "name": "Кошачье вмешательство",
        "path": "tres3/",
        "file": "M3gold017.gif"
    }, {
        "name": "Выбери меня",
        "path": "tres3/",
        "file": "M3gold018.gif"
    }, {
        "name": "Универсальный размер",
        "path": "tres3/",
        "file": "M3gold019.gif"
    }, {
        "name": "Ножная булава",
        "path": "tres3/",
        "file": "M3gold020.gif"
    }, {
        "name": "Ворпальный меч",
        "path": "tres3/",
        "file": "M3gold021.gif"
    }, {
        "name": "Жгучий соус",
        "path": "tres3/",
        "file": "M3gold022.gif"
    }, {
        "name": "Ароматерный пирог",
        "path": "tres3/",
        "file": "M3gold023.gif"
    }, {
        "name": "Великолепная шляпа",
        "path": "tres3/",
        "file": "M3gold024.gif"
    }, {
        "name": "Блестящие кубики кручу-верчу. Получи уровень",
        "path": "tres3/",
        "file": "M3gold025.gif"
    }, {
        "name": "Зелье апатии",
        "path": "tres3/",
        "file": "M3gold026.gif"
    }, {
        "name": "Утка много чего",
        "path": "tres3/",
        "file": "M3gold027.gif"
    }, {
        "name": "Лич Бич",
        "path": "tres3/",
        "file": "M3gold028.gif"
    }, {
        "name": "Нарисуй своего персонажа. Получи уровень",
        "path": "tres3/",
        "file": "M3gold029.gif"
    }, {
        "name": "Женщина настойка",
        "path": "tres3/",
        "file": "M3gold030.gif"
    }, {
        "name": "Хотельное кольцо",
        "path": "tres3/",
        "file": "M3gold031.gif"
    }, {
        "name": "Гномексовый комбез",
        "path": "tres3/",
        "file": "M3gold032.gif"
    }, {
        "name": "Вспомни о днюхе мастера. Получи уровень",
        "path": "tres3/",
        "file": "M3gold033.gif"
    }, {
        "name": "Читерский кубик",
        "path": "tres3/",
        "file": "M3gold034.gif"
    }, {
        "name": "Ролевое ложе",
        "path": "tres3/",
        "file": "M3gold035.gif"
    }, {
        "name": "Авторезарь",
        "path": "tres3/",
        "file": "M3gold036.gif"
    }, {
        "name": "Наемничек",
        "path": "tres3/",
        "file": "M3gold037.gif"
    }, {
        "name": "Перепиши старую грязную карточку персонажа. Получи уровень",
        "path": "tres3/",
        "file": "M3gold038.gif"
    }, {
        "name": "Монстрячий корм",
        "path": "tres3/",
        "file": "M3gold039.gif"
    }, {
        "name": "С боку ручки",
        "path": "tres3/",
        "file": "M3gold040.gif"
    }, {
        "name": "Подземное казино",
        "path": "tres3/",
        "file": "M3gold041.gif"
    }, {
        "name": "Розззыгрыжжж",
        "path": "tres3/",
        "file": "M3gold042.gif"
    }, {
        "name": "Бессмысленный жест доброй воли. Получи уровень",
        "path": "tres3/",
        "file": "M3gold043.gif"
    }, {
        "name": "Зажигательная смесь",
        "path": "tres3/",
        "file": "M3gold044.gif"
    }, {
        "name": "Бог из автомата",
        "path": "tres3/",
        "file": "M3gold045.gif"
    }, {
        "name": "Иногда полезный амулет",
        "path": "tres3/",
        "file": "M3gold046.gif"
    }]
}